main.py
pyspecan/__init__.py
pyspecan/__main__.py
pyspecan/config.py
pyspecan/err.py
pyspecan/logger.py
pyspecan/specan.py
pyspecan/_internal/__init__.py
pyspecan/_internal/main.py
pyspecan/backend/__init__.py
pyspecan/backend/mpl/__init__.py
pyspecan/backend/mpl/ax.py
pyspecan/backend/mpl/color.py
pyspecan/backend/mpl/plot.py
pyspecan/backend/mpl/theme.py
pyspecan/backend/tk/__init__.py
pyspecan/backend/tk/_theme.py
pyspecan/backend/tk/theme.py
pyspecan/backend/tk/widgets/__init__.py
pyspecan/backend/tk/widgets/scale.py
pyspecan/controller/__init__.py
pyspecan/controller/base.py
pyspecan/controller/controller.py
pyspecan/controller/cui.py
pyspecan/controller/tk_gui.py
pyspecan/controller/CUI/__init__.py
pyspecan/controller/CUI/base.py
pyspecan/controller/CUI/plot_base.py
pyspecan/controller/tkGUI/__init__.py
pyspecan/controller/tkGUI/base.py
pyspecan/controller/tkGUI/dispatch.py
pyspecan/controller/tkGUI/mode.py
pyspecan/controller/tkGUI/mode_rt.py
pyspecan/controller/tkGUI/mode_swept.py
pyspecan/controller/tkGUI/panels.py
pyspecan/controller/tkGUI/plot_base.py
pyspecan/controller/tkGUI/sink.py
pyspecan/controller/tkGUI/sink_file.py
pyspecan/controller/tkGUI/sink_live.py
pyspecan/controller/tkGUI/rt/__init__.py
pyspecan/controller/tkGUI/rt/pst.py
pyspecan/controller/tkGUI/rt/spg.py
pyspecan/controller/tkGUI/shared/__init__.py
pyspecan/controller/tkGUI/shared/iq.py
pyspecan/controller/tkGUI/shared/iq3d.py
pyspecan/controller/tkGUI/shared/phasor.py
pyspecan/controller/tkGUI/shared/pmf.py
pyspecan/controller/tkGUI/swept/__init__.py
pyspecan/controller/tkGUI/swept/freq.py
pyspecan/controller/tkGUI/swept/psd.py
pyspecan/controller/tkGUI/swept/spg.py
pyspecan/controller/tkGUI/swept/spg3d.py
pyspecan/model/__init__.py
pyspecan/model/base.py
pyspecan/model/model.py
pyspecan/model/mode/__init__.py
pyspecan/model/mode/mode.py
pyspecan/model/mode/rt.py
pyspecan/model/mode/swept.py
pyspecan/model/sink/__init__.py
pyspecan/model/sink/file.py
pyspecan/model/sink/live.py
pyspecan-0.5.1.dist-info/licenses/LICENSE
pyspecan-0.5.1.dist-info/METADATA
pyspecan-0.5.1.dist-info/WHEEL
pyspecan-0.5.1.dist-info/entry_points.txt
pyspecan-0.5.1.dist-info/top_level.txt
pyspecan-0.5.1.dist-info/RECORD
