Metadata-Version: 2.4
Name: pyspecan
Version: 0.5.1
Summary: A spectrum analyzer library
Author-email: Anonoei <to+dev@an0.cx>
License-Expression: MIT
Project-URL: Homepage, https://github.com/anonoei/pyspecan
Project-URL: Documentation, https://anonoei.github.io/pyspecan/
Project-URL: Repository, https://github.com/Anonoei/pyspecan.git
Project-URL: Issues, https://github.com/Anonoei/pyspecan/issues
Project-URL: Source, https://github.com/anonoei/pyspecan
Keywords: anonoei,sdr,speca,specan
Classifier: Development Status :: 4 - Beta
Classifier: Intended Audience :: Developers
Classifier: Programming Language :: Python :: 3
Classifier: Operating System :: OS Independent
Requires-Python: >=3.8
License-File: LICENSE
Requires-Dist: numpy
Requires-Dist: matplotlib
Provides-Extra: dev
Requires-Dist: twine; extra == "dev"
Requires-Dist: build; extra == "dev"
Requires-Dist: bumpver; extra == "dev"
Requires-Dist: pytest; extra == "dev"
Requires-Dist: pdoc3; extra == "dev"
Dynamic: license-file
